dashboard/__init__.py
dashboard/apps.py
dashboard/models.py
dashboard/urls.py
dashboard/views.py
dashboard/middleware/middlewares.py
dashboard/static/css/dashboard.css
dashboard/static/css/main.686e66b5.chunk.css
dashboard/static/css/main.7bba74c4.chunk.css
dashboard/static/css/main.7c855221.chunk.css
dashboard/static/js/1.72577c1f.chunk.js
dashboard/static/js/1.81b65d9b.chunk.js
dashboard/static/js/1.a83f1ce1.chunk.js
dashboard/static/js/dashboard.js
dashboard/static/js/main.1a2bb8a2.chunk.js
dashboard/static/js/main.4b179a20.chunk.js
dashboard/static/js/main.9eb95ed4.chunk.js
dashboard/static/js/main.a9e65f07.chunk.js
dashboard/static/js/runtime~main.229c360f.js
dashboard/templates/dashboard/index.html
dashboard/utility/__init__.py
dashboard/utility/helper.py
dj_dash_repo-0.1.0.dist-info/DESCRIPTION.rst
dj_dash_repo-0.1.0.dist-info/METADATA
dj_dash_repo-0.1.0.dist-info/RECORD
dj_dash_repo-0.1.0.dist-info/WHEEL
dj_dash_repo-0.1.0.dist-info/metadata.json
dj_dash_repo-0.1.0.dist-info/top_level.txt
