Metadata-Version: 2.0
Name: dj-dash-repo
Version: 0.1.0
Summary: This is package for django site analytics
Home-page: https://github.com/rahul1809/dj-dash-repo
Author: rahul mishra
Author-email: rahul.mishra2003@gmail.com
License: MIT
Keywords: dj-dash-repo
Platform: UNKNOWN
Classifier: Development Status :: 3 - Alpha
Classifier: Framework :: Django :: 2.0
Classifier: Intended Audience :: Developers
Classifier: License :: OSI Approved :: BSD License
Classifier: Natural Language :: English
Classifier: Programming Language :: Python :: 2
Classifier: Programming Language :: Python :: 2.7
Classifier: Programming Language :: Python :: 3
Classifier: Programming Language :: Python :: 3.4
Classifier: Programming Language :: Python :: 3.5
Classifier: Programming Language :: Python :: 3.6
Requires-Dist: requests
